sheetconnect/__init__.py
sheetconnect/sheetconnect.py
sheetconnect-1.0.2.dist-info/METADATA
sheetconnect-1.0.2.dist-info/WHEEL
sheetconnect-1.0.2.dist-info/top_level.txt
sheetconnect-1.0.2.dist-info/RECORD
