Metadata-Version: 2.1
Name: sheetconnect
Version: 1.0.2
Summary: Simple get data from Google sheet in form of Pandas dataframe
Author: Pongsakorn Nimphaya
Requires-Python: >=3.6
